jampy/CHANGELOG.rst
jampy/LICENSE.txt
jampy/README.rst
jampy/__init__.py
jampy/axi/__init__.py
jampy/axi/jam_axi_intr.py
jampy/axi/jam_axi_proj.py
jampy/axi/jam_axi_sersic.py
jampy/examples/__init__.py
jampy/examples/cappellari2020_table1.txt
jampy/examples/jam_axi_intr_example.py
jampy/examples/jam_axi_proj_example.py
jampy/examples/jam_black_hole_bayes_example.py
jampy/examples/jam_black_hole_capfit_example.py
jampy/examples/jam_dark_halo_bayes_example.py
jampy/examples/jam_hernquist_model_example.py
jampy/examples/jam_mock_kinematics_black_hole.txt
jampy/examples/jam_mock_kinematics_dark_halo.txt
jampy/examples/jam_sph_proj_example.py
jampy/examples/mge_vcirc_example.py
jampy/mge/__init__.py
jampy/mge/mge_cylindrical_mass.py
jampy/mge/mge_half_light_isophote.py
jampy/mge/mge_radial_density.py
jampy/mge/mge_radial_mass.py
jampy/mge/mge_vcirc.py
jampy/mge/mge_weighted_slope.py
jampy/sph/__init__.py
jampy/sph/jam_sph_intr.py
jampy/sph/jam_sph_proj.py
jampy/util/__init__.py
jampy/util/betax.py
jampy/util/cosmology_distance.py
jampy/util/quad1d.py
jampy/util/quad2d.py
jampy-8.1.4.dist-info/METADATA
jampy-8.1.4.dist-info/WHEEL
jampy-8.1.4.dist-info/top_level.txt
jampy-8.1.4.dist-info/zip-safe
jampy-8.1.4.dist-info/RECORD
